torchrecord/__init__.py
torchrecord/dataloader.py
torchrecord/dataset.py
torchrecord/record.py
torchrecord/sampler.py
torchrecord/tr_pb2.py
torchrecord/transforms.py
torchrecord/writer.py
torchrecord-0.1.1.dist-info/METADATA
torchrecord-0.1.1.dist-info/WHEEL
torchrecord-0.1.1.dist-info/top_level.txt
torchrecord-0.1.1.dist-info/RECORD
